{
  "permissions": "/runtime/fundamentals/security/",
  "config": "/runtime/fundamentals/configuration/",
  "ide": "/runtime/getting_started/setup_your_environment/#setting-up-your-editor%2Fide",
  "import_maps": "/runtime/manual/basics/import_maps",
  "--allow-env": "/runtime/fundamentals/security/#environment-access",
  "--allow-ffi": "/runtime/fundamentals/security/#ffi-(foreign-function-interface)",
  "--allow-hrtime": "/runtime/fundamentals/security/#high-resolution-time",
  "--allow-net": "/runtime/fundamentals/security/#network-access",
  "--allow-read": "/runtime/fundamentals/security/#file-system-read-access",
  "--allow-run": "/runtime/fundamentals/security/#running-subprocesses",
  "--allow-sys": "/runtime/fundamentals/security/#system-information",
  "--allow-write": "/runtime/fundamentals/security/#file-system-write-access",
  "--allow-all": "/runtime/fundamentals/security/#all-permissions",
  "--allow-import": "/runtime/fundamentals/security/#importing-from-the-web",
  "--unsafely-ignore-certificate-errors": "/runtime/fundamentals/security/#tls-certificates-errors",
  "bench": "/runtime/manual/tools/benchmarker",
  "cache": "/runtime/manual/tools/cache",
  "check": "/runtime/manual/tools/check",
  "compile": "/runtime/manual/tools/compiler",
  "coverage": "/runtime/manual/tools/coverage",
  "doc": "/runtime/manual/tools/documentation_generator",
  "eval": "/runtime/manual/tools/eval",
  "fmt": "/runtime/manual/tools/formatter",
  "info": "/runtime/manual/tools/dependency_inspector",
  "lint": "/runtime/manual/tools/linter",
  "run": "/runtime/manual/tools/run",
  "serve": "/runtime/manual/tools/serve",
  "test": "/runtime/manual/tools/test",
  "upgrade": "/runtime/manual/tools/upgrade",
  "env-vars": "/runtime/reference/env_variables"
}
