{
  "unversionedId": "manual/ci_github",
  "id": "manual/ci_github",
  "title": "CI and GitHub Actions",
  "description": "Deno Deploy's Git integration enables deployment of code changes that are pushed",
  "source": "@site/deploy/manual/ci_github.md",
  "sourceDirName": "manual",
  "slug": "/manual/ci_github",
  "permalink": "/deploy/manual/ci_github",
  "draft": false,
  "tags": [],
  "version": "current",
  "frontMatter": {},
  "sidebar": "deployGuideHome",
  "previous": {
    "title": "Deploy with GitHub integration",
    "permalink": "/deploy/manual/how-to-deploy"
  },
  "next": {
    "title": "Using deployctl on the command line",
    "permalink": "/deploy/manual/deployctl"
  }
}
